tarefa_3/componentes/pc.v
module pc(
    input clk,
    input load,
    input increment,
    output reg [15:0] count
);

    always @(posedge clk) begin
        if (load) begin
            count <= load;
        end else if (increment) begin
            count <= count + 1;
        end
    end

endmodule

tarefa_3/Tb/tb_pc.v
`include "../componentes/pc.v"

module tb_pc;

    reg clk;
    reg load;
    reg increment;
    wire [15:0] count;

    pc uut (
        .clk(clk),
        .load(load),
        .increment(increment),
        .count(count)
    );

    initial begin
        $dumpfile("signals.vcd");
        $dumpvars(0);
        clk = 0;
        load = 0;
        increment = 0;

        #1 load = 1;
        #1 increment = 1;
        #1 load = 0;
        #1 increment = 0;
        #1 increment = 1 ;
        #10;

        $finish;

    end

    always #1 clk = ~clk;

endmodule

tarefa_3/Tb/signals.vcd
$date
	Sun Aug 25 20:19:47 2024
$end
$version
	Icarus Verilog
$end
$timescale
	1s
$end
$scope module tb_pc $end
$var wire 16 ! count [15:0] $end
$var reg 1 " clk $end
$var reg 1 # increment $end
$var reg 1 $ load $end
$scope module uut $end
$var wire 1 " clk $end
$var wire 1 # increment $end
$var wire 1 $ load $end
$var reg 16 % count [15:0] $end
$upscope $end
$upscope $end
$enddefinitions $end
$comment Show the parameter values. $end
$dumpall
$end
#0
$dumpvars
bx %
0$
0#
0"
bx !
$end
#1
b1 !
b1 %
1"
1$
#2
0"
1#
#3
b10 !
b10 %
1"
0$
#4
0"
0#
#5
b11 !
b11 %
1"
1#
#6
0"
#7
b100 !
b100 %
1"
#8
0"
#9
b101 !
b101 %
1"
#10
0"
#11
b110 !
b110 %
1"
#12
0"
#13
b111 !
b111 %
1"
#14
0"
#15
b1000 !
b1000 %
1"
