tarefa_2/ALUs/halfadder.v
module halfadder(
    input a,
    input b,
    output soma,
    output carry
);

    assign soma = a ^ b; // XOR entre a e b é a soma entre os dois numeros
    assign carry = a & b; // o carry é a operação AND entre a e b
endmodule

Tarefa5/fulladder.v
`include "../Tarefa5/halfadder.v"

module fulladder(
    input a,
    input b,
    input carry_in,
    output sum,
    output carry_out
);

    wire s1, c1, c2;

    halfadder uut1(.a(a), .b(b), .soma(s1), .carry(c1));
    halfadder uut2(.a(s1), .b(carry_in), .soma(sum), .carry(c2));
    assign carry_out = c1 | c2;
endmodule

Tarefa5/add16.v
`include "../Tarefa5/fulladder.v"

module add16bits(
    input wire [15:0] a,
    input wire [15:0] b,
    input carry_in,
    output [15:0] sum,
    output carry_out
);
    wire [15:0] carry;
    wire [15:0] sum_temp;

    fulladder fa0(.a(a[0]), .b(b[0]), .carry_in(carry_in), .sum(sum_temp[0]), .carry_out(carry[0]));
    fulladder fa1(.a(a[1]), .b(b[1]), .carry_in(carry[0]), .sum(sum_temp[1]), .carry_out(carry[1]));
    fulladder fa2(.a(a[2]), .b(b[2]), .carry_in(carry[1]), .sum(sum_temp[2]), .carry_out(carry[2]));
    fulladder fa3(.a(a[3]), .b(b[3]), .carry_in(carry[2]), .sum(sum_temp[3]), .carry_out(carry[3]));
    fulladder fa4(.a(a[4]), .b(b[4]), .carry_in(carry[3]), .sum(sum_temp[4]), .carry_out(carry[4]));
    fulladder fa5(.a(a[5]), .b(b[5]), .carry_in(carry[4]), .sum(sum_temp[5]), .carry_out(carry[5]));
    fulladder fa6(.a(a[6]), .b(b[6]), .carry_in(carry[5]), .sum(sum_temp[6]), .carry_out(carry[6]));
    fulladder fa7(.a(a[7]), .b(b[7]), .carry_in(carry[6]), .sum(sum_temp[7]), .carry_out(carry[7]));
    fulladder fa8(.a(a[8]), .b(b[8]), .carry_in(carry[7]), .sum(sum_temp[8]), .carry_out(carry[8]));
    fulladder fa9(.a(a[9]), .b(b[9]), .carry_in(carry[8]), .sum(sum_temp[9]), .carry_out(carry[9]));
    fulladder fa10(.a(a[10]), .b(b[10]), .carry_in(carry[9]), .sum(sum_temp[10]), .carry_out(carry[10]));
    fulladder fa11(.a(a[11]), .b(b[11]), .carry_in(carry[10]), .sum(sum_temp[11]), .carry_out(carry[11]));
    fulladder fa12(.a(a[12]), .b(b[12]), .carry_in(carry[11]), .sum(sum_temp[12]), .carry_out(carry[12]));
    fulladder fa13(.a(a[13]), .b(b[13]), .carry_in(carry[12]), .sum(sum_temp[13]), .carry_out(carry[13]));
    fulladder fa14(.a(a[14]), .b(b[14]), .carry_in(carry[13]), .sum(sum_temp[14]), .carry_out(carry[14]));
    fulladder fa15(.a(a[15]), .b(b[15]), .carry_in(carry[14]), .sum(sum_temp[15]), .carry_out(carry[15]));

    assign sum = sum_temp;
    assign carry_out = carry[15];
endmodule

Tarefa5/RAM16K.v
module ram16384(
    input [13:0] address,
    input [15:0] data_in,
    input write_enable,
    input clk,
    output [15:0] data_out
);
    reg [15:0] memory [0:16383];
    
    always @(posedge clk) begin
        if (write_enable)
            memory[address] <= data_in;
    end
    
    assign data_out = memory[address];
endmodule

Tarefa5/hack_alu.v
`include "../Tarefa5/add16.v"

module hack_alu(
    input [15:0] X,
    input [15:0] Y,
    input zX, nX, zY, nY, f, no,
    output [15:0] out,
    output carry_out
);

reg [15:0] X_reg;
reg [15:0] Y_reg;
reg [15:0] out_reg;

always @(zX or nX or zY or nY or f or no) begin
    if(zX) begin
        X_reg = 0;
    end else begin
        X_reg = X;
    end
    if(nX) begin
        X_reg = ~X;
    end
    if(zY) begin
        Y_reg = 16'h0000;
    end else begin
        Y_reg = Y;
    end
    if(nY) begin
        Y_reg = ~Y;
    end
    if(no) begin
        out_reg = X_reg & Y_reg;
    end
    if(f) begin
        out_reg = X_reg + Y_reg;
    end
end

assign out = out_reg;

endmodule

Tarefa5/cpu.v
`include "../Tarefa5/hack_alu.v"
`include "../Tarefa5/RAM16K.v"

module CPU (
    input wire [15:0] inM,
    input wire [15:0] instruction,
    input wire reset,
    input wire clk,
    output reg [15:0] outM,
    output reg writeM,
    output reg [15:0] addressM,
    output reg [15:0] pc
);

    reg [15:0] A;
    reg [15:0] D;
    reg [14:0] nextPC;

    wire isCInstruction;
    wire isAInstruction;
    wire [15:0] aluOut;
    wire aluZero, aluNeg;

    assign isAInstruction = ~instruction[15];
    assign isCInstruction = instruction[15];

    hack_alu alu (
        .X(D),
        .Y(instruction[12] ? inM : A),
        .zX(instruction[11]),
        .nX(instruction[10]),
        .zY(instruction[9]),
        .nY(instruction[8]),
        .f(instruction[7]),
        .no(instruction[6]),
        .out(aluOut),
        .carry_out(aluZero)
    );

    ram16384 memory (
        .address(pc[14:0]),
        .data_in(inM),
        .write_enable(writeM),
        .clk(clk)
    );

    always @(posedge clk or posedge reset) begin
        if (reset)
            pc <= 16'd0;
        else
            pc <= nextPC;
    end

    always @(posedge clk) begin
        if (isAInstruction) begin
            A <= instruction;
        end else if (isCInstruction) begin
            if (instruction[5]) D <= aluOut;
            if (instruction[4]) A <= aluOut;
            if (instruction[3]) outM <= aluOut;
            writeM <= instruction[3];
            addressM <= A[14:0];
            if ((instruction[2] && aluNeg) ||
                (instruction[1] && aluZero) ||
                (instruction[0] && !aluNeg && !aluZero))
                nextPC <= A[14:0];
            else
                nextPC <= nextPC + 1;
            pc <= nextPC;
        end
    end
endmodule

Tarefa5/tb_cpu.v
`include "cpu.v"

module CPU_tb;
    reg [15:0] inM;
    reg [15:0] instruction;
    reg clk;
    reg reset;
    wire [15:0] outM;
    wire writeM;
    wire [14:0] addressM;
    wire [14:0] pc;

    CPU cpu(.inM(inM), .instruction(instruction), .clk(clk), .reset(reset),
            .outM(outM), .writeM(writeM), .addressM(addressM), .pc(pc));

    always #5 clk = ~clk;

    initial begin
        $dumpfile("signals.vcd");
        $dumpvars(0);
        clk = 0;
        reset = 1;
        #10 reset = 0;

        instruction = 16'b0000000000001111;
        #10;

        instruction = 16'b1110110000010000;
        #10;

        instruction = 16'b0000000000000001;
        #10;

        instruction = 16'b1110001100001000;
        inM = 16'hABCD;
        #10;

        instruction = 16'b1110000010000000;
        inM = 16'h1234;
        instruction = 16'h5678;
        #10;

        instruction = 16'b1111000000010000;
        inM = 16'hABCD;
        instruction = 16'h1234;
        #10;

        instruction = 16'b1111000000001000;
        instruction = 16'h0001;
        #10;

        instruction = 16'b1110000010001000;
        instruction = 16'h0001;
        #10;

        #50 $finish;
    end
endmodule

Tarefa5/signals.vcd
$date
	Sat Sep 28 12:59:26 2024
$end
$version
	Icarus Verilog
$end
$timescale
	1s
$end
$scope module CPU_tb $end
$var wire 1 ! writeM $end
$var wire 15 " pc [14:0] $end
$var wire 16 # outM [15:0] $end
$var wire 15 $ addressM [14:0] $end
$var reg 1 % clk $end
$var reg 16 & inM [15:0] $end
$var reg 16 ' instruction [15:0] $end
$var reg 1 ( reset $end
$scope module cpu $end
$var wire 1 ) aluNeg $end
$var wire 1 * aluZero $end
$var wire 1 % clk $end
$var wire 16 + inM [15:0] $end
$var wire 16 , instruction [15:0] $end
$var wire 1 - isAInstruction $end
$var wire 1 ( reset $end
$var wire 1 . isCInstruction $end
$var wire 16 / aluOut [15:0] $end
$var reg 16 0 A [15:0] $end
$var reg 16 1 D [15:0] $end
$var reg 16 2 addressM [15:0] $end
$var reg 15 3 nextPC [14:0] $end
$var reg 16 4 outM [15:0] $end
$var reg 16 5 pc [15:0] $end
$var reg 1 ! writeM $end
$scope module alu $end
$var wire 16 6 X [15:0] $end
$var wire 16 7 Y [15:0] $end
$var wire 1 * carry_out $end
$var wire 1 8 f $end
$var wire 1 9 nX $end
$var wire 1 : nY $end
$var wire 1 ; no $end
$var wire 16 < out [15:0] $end
$var wire 1 = zX $end
$var wire 1 > zY $end
$var reg 16 ? X_reg [15:0] $end
$var reg 16 @ Y_reg [15:0] $end
$var reg 16 A out_reg [15:0] $end
$upscope $end
$scope module memory $end
$var wire 14 B address [13:0] $end
$var wire 1 % clk $end
$var wire 16 C data_in [15:0] $end
$var wire 16 D data_out [15:0] $end
$var wire 1 ! write_enable $end
$upscope $end
$upscope $end
$upscope $end
$scope module add16bits $end
$var wire 16 E a [15:0] $end
$var wire 16 F b [15:0] $end
$var wire 1 G carry_in $end
$var wire 16 H sum [15:0] $end
$var wire 16 I sum_temp [15:0] $end
$var wire 1 J carry_out $end
$var wire 16 K carry [15:0] $end
$scope module fa0 $end
$var wire 1 L a $end
$var wire 1 M b $end
$var wire 1 G carry_in $end
$var wire 1 N carry_out $end
$var wire 1 O sum $end
$var wire 1 P s1 $end
$var wire 1 Q c2 $end
$var wire 1 R c1 $end
$scope module uut1 $end
$var wire 1 L a $end
$var wire 1 M b $end
$var wire 1 R carry $end
$var wire 1 P soma $end
$upscope $end
$scope module uut2 $end
$var wire 1 P a $end
$var wire 1 G b $end
$var wire 1 Q carry $end
$var wire 1 O soma $end
$upscope $end
$upscope $end
$scope module fa1 $end
$var wire 1 S a $end
$var wire 1 T b $end
$var wire 1 U carry_in $end
$var wire 1 V carry_out $end
$var wire 1 W sum $end
$var wire 1 X s1 $end
$var wire 1 Y c2 $end
$var wire 1 Z c1 $end
$scope module uut1 $end
$var wire 1 S a $end
$var wire 1 T b $end
$var wire 1 Z carry $end
$var wire 1 X soma $end
$upscope $end
$scope module uut2 $end
$var wire 1 X a $end
$var wire 1 U b $end
$var wire 1 Y carry $end
$var wire 1 W soma $end
$upscope $end
$upscope $end
$scope module fa10 $end
$var wire 1 [ a $end
$var wire 1 \ b $end
$var wire 1 ] carry_in $end
$var wire 1 ^ carry_out $end
$var wire 1 _ sum $end
$var wire 1 ` s1 $end
$var wire 1 a c2 $end
$var wire 1 b c1 $end
$scope module uut1 $end
$var wire 1 [ a $end
$var wire 1 \ b $end
$var wire 1 b carry $end
$var wire 1 ` soma $end
$upscope $end
$scope module uut2 $end
$var wire 1 ` a $end
$var wire 1 ] b $end
$var wire 1 a carry $end
$var wire 1 _ soma $end
$upscope $end
$upscope $end
$scope module fa11 $end
$var wire 1 c a $end
$var wire 1 d b $end
$var wire 1 e carry_in $end
$var wire 1 f carry_out $end
$var wire 1 g sum $end
$var wire 1 h s1 $end
$var wire 1 i c2 $end
$var wire 1 j c1 $end
$scope module uut1 $end
$var wire 1 c a $end
$var wire 1 d b $end
$var wire 1 j carry $end
$var wire 1 h soma $end
$upscope $end
$scope module uut2 $end
$var wire 1 h a $end
$var wire 1 e b $end
$var wire 1 i carry $end
$var wire 1 g soma $end
$upscope $end
$upscope $end
$scope module fa12 $end
$var wire 1 k a $end
$var wire 1 l b $end
$var wire 1 m carry_in $end
$var wire 1 n carry_out $end
$var wire 1 o sum $end
$var wire 1 p s1 $end
$var wire 1 q c2 $end
$var wire 1 r c1 $end
$scope module uut1 $end
$var wire 1 k a $end
$var wire 1 l b $end
$var wire 1 r carry $end
$var wire 1 p soma $end
$upscope $end
$scope module uut2 $end
$var wire 1 p a $end
$var wire 1 m b $end
$var wire 1 q carry $end
$var wire 1 o soma $end
$upscope $end
$upscope $end
$scope module fa13 $end
$var wire 1 s a $end
$var wire 1 t b $end
$var wire 1 u carry_in $end
$var wire 1 v carry_out $end
$var wire 1 w sum $end
$var wire 1 x s1 $end
$var wire 1 y c2 $end
$var wire 1 z c1 $end
$scope module uut1 $end
$var wire 1 s a $end
$var wire 1 t b $end
$var wire 1 z carry $end
$var wire 1 x soma $end
$upscope $end
$scope module uut2 $end
$var wire 1 x a $end
$var wire 1 u b $end
$var wire 1 y carry $end
$var wire 1 w soma $end
$upscope $end
$upscope $end
$scope module fa14 $end
$var wire 1 { a $end
$var wire 1 | b $end
$var wire 1 } carry_in $end
$var wire 1 ~ carry_out $end
$var wire 1 !" sum $end
$var wire 1 "" s1 $end
$var wire 1 #" c2 $end
$var wire 1 $" c1 $end
$scope module uut1 $end
$var wire 1 { a $end
$var wire 1 | b $end
$var wire 1 $" carry $end
$var wire 1 "" soma $end
$upscope $end
$scope module uut2 $end
$var wire 1 "" a $end
$var wire 1 } b $end
$var wire 1 #" carry $end
$var wire 1 !" soma $end
$upscope $end
$upscope $end
$scope module fa15 $end
$var wire 1 %" a $end
$var wire 1 &" b $end
$var wire 1 '" carry_in $end
$var wire 1 (" carry_out $end
$var wire 1 )" sum $end
$var wire 1 *" s1 $end
$var wire 1 +" c2 $end
$var wire 1 ," c1 $end
$scope module uut1 $end
$var wire 1 %" a $end
$var wire 1 &" b $end
$var wire 1 ," carry $end
$var wire 1 *" soma $end
$upscope $end
$scope module uut2 $end
$var wire 1 *" a $end
$var wire 1 '" b $end
$var wire 1 +" carry $end
$var wire 1 )" soma $end
$upscope $end
$upscope $end
$scope module fa2 $end
$var wire 1 -" a $end
$var wire 1 ." b $end
$var wire 1 /" carry_in $end
$var wire 1 0" carry_out $end
$var wire 1 1" sum $end
$var wire 1 2" s1 $end
$var wire 1 3" c2 $end
$var wire 1 4" c1 $end
$scope module uut1 $end
$var wire 1 -" a $end
$var wire 1 ." b $end
$var wire 1 4" carry $end
$var wire 1 2" soma $end
$upscope $end
$scope module uut2 $end
$var wire 1 2" a $end
$var wire 1 /" b $end
$var wire 1 3" carry $end
$var wire 1 1" soma $end
$upscope $end
$upscope $end
$scope module fa3 $end
$var wire 1 5" a $end
$var wire 1 6" b $end
$var wire 1 7" carry_in $end
$var wire 1 8" carry_out $end
$var wire 1 9" sum $end
$var wire 1 :" s1 $end
$var wire 1 ;" c2 $end
$var wire 1 <" c1 $end
$scope module uut1 $end
$var wire 1 5" a $end
$var wire 1 6" b $end
$var wire 1 <" carry $end
$var wire 1 :" soma $end
$upscope $end
$scope module uut2 $end
$var wire 1 :" a $end
$var wire 1 7" b $end
$var wire 1 ;" carry $end
$var wire 1 9" soma $end
$upscope $end
$upscope $end
$scope module fa4 $end
$var wire 1 =" a $end
$var wire 1 >" b $end
$var wire 1 ?" carry_in $end
$var wire 1 @" carry_out $end
$var wire 1 A" sum $end
$var wire 1 B" s1 $end
$var wire 1 C" c2 $end
$var wire 1 D" c1 $end
$scope module uut1 $end
$var wire 1 =" a $end
$var wire 1 >" b $end
$var wire 1 D" carry $end
$var wire 1 B" soma $end
$upscope $end
$scope module uut2 $end
$var wire 1 B" a $end
$var wire 1 ?" b $end
$var wire 1 C" carry $end
$var wire 1 A" soma $end
$upscope $end
$upscope $end
$scope module fa5 $end
$var wire 1 E" a $end
$var wire 1 F" b $end
$var wire 1 G" carry_in $end
$var wire 1 H" carry_out $end
$var wire 1 I" sum $end
$var wire 1 J" s1 $end
$var wire 1 K" c2 $end
$var wire 1 L" c1 $end
$scope module uut1 $end
$var wire 1 E" a $end
$var wire 1 F" b $end
$var wire 1 L" carry $end
$var wire 1 J" soma $end
$upscope $end
$scope module uut2 $end
$var wire 1 J" a $end
$var wire 1 G" b $end
$var wire 1 K" carry $end
$var wire 1 I" soma $end
$upscope $end
$upscope $end
$scope module fa6 $end
$var wire 1 M" a $end
$var wire 1 N" b $end
$var wire 1 O" carry_in $end
$var wire 1 P" carry_out $end
$var wire 1 Q" sum $end
$var wire 1 R" s1 $end
$var wire 1 S" c2 $end
$var wire 1 T" c1 $end
$scope module uut1 $end
$var wire 1 M" a $end
$var wire 1 N" b $end
$var wire 1 T" carry $end
$var wire 1 R" soma $end
$upscope $end
$scope module uut2 $end
$var wire 1 R" a $end
$var wire 1 O" b $end
$var wire 1 S" carry $end
$var wire 1 Q" soma $end
$upscope $end
$upscope $end
$scope module fa7 $end
$var wire 1 U" a $end
$var wire 1 V" b $end
$var wire 1 W" carry_in $end
$var wire 1 X" carry_out $end
$var wire 1 Y" sum $end
$var wire 1 Z" s1 $end
$var wire 1 [" c2 $end
$var wire 1 \" c1 $end
$scope module uut1 $end
$var wire 1 U" a $end
$var wire 1 V" b $end
$var wire 1 \" carry $end
$var wire 1 Z" soma $end
$upscope $end
$scope module uut2 $end
$var wire 1 Z" a $end
$var wire 1 W" b $end
$var wire 1 [" carry $end
$var wire 1 Y" soma $end
$upscope $end
$upscope $end
$scope module fa8 $end
$var wire 1 ]" a $end
$var wire 1 ^" b $end
$var wire 1 _" carry_in $end
$var wire 1 `" carry_out $end
$var wire 1 a" sum $end
$var wire 1 b" s1 $end
$var wire 1 c" c2 $end
$var wire 1 d" c1 $end
$scope module uut1 $end
$var wire 1 ]" a $end
$var wire 1 ^" b $end
$var wire 1 d" carry $end
$var wire 1 b" soma $end
$upscope $end
$scope module uut2 $end
$var wire 1 b" a $end
$var wire 1 _" b $end
$var wire 1 c" carry $end
$var wire 1 a" soma $end
$upscope $end
$upscope $end
$scope module fa9 $end
$var wire 1 e" a $end
$var wire 1 f" b $end
$var wire 1 g" carry_in $end
$var wire 1 h" carry_out $end
$var wire 1 i" sum $end
$var wire 1 j" s1 $end
$var wire 1 k" c2 $end
$var wire 1 l" c1 $end
$scope module uut1 $end
$var wire 1 e" a $end
$var wire 1 f" b $end
$var wire 1 l" carry $end
$var wire 1 j" soma $end
$upscope $end
$scope module uut2 $end
$var wire 1 j" a $end
$var wire 1 g" b $end
$var wire 1 k" carry $end
$var wire 1 i" soma $end
$upscope $end
$upscope $end
$upscope $end
$enddefinitions $end
$comment Show the parameter values. $end
$dumpall
$end
#0
$dumpvars
xl"
xk"
xj"
xi"
xh"
xg"
zf"
ze"
xd"
xc"
xb"
xa"
x`"
x_"
z^"
z]"
x\"
x["
xZ"
xY"
xX"
xW"
zV"
zU"
xT"
xS"
xR"
xQ"
xP"
xO"
zN"
zM"
xL"
xK"
xJ"
xI"
xH"
xG"
zF"
zE"
xD"
xC"
xB"
xA"
x@"
x?"
z>"
z="
x<"
x;"
x:"
x9"
x8"
x7"
z6"
z5"
x4"
x3"
x2"
x1"
x0"
x/"
z."
z-"
x,"
x+"
x*"
x)"
x("
x'"
z&"
z%"
x$"
x#"
x""
x!"
x~
x}
z|
z{
xz
xy
xx
xw
xv
xu
zt
zs
xr
xq
xp
xo
xn
xm
zl
zk
xj
xi
xh
xg
xf
xe
zd
zc
xb
xa
x`
x_
x^
x]
z\
z[
xZ
xY
xX
xW
xV
xU
zT
zS
xR
xQ
xP
xO
xN
zM
zL
bx K
xJ
bx I
bx H
zG
bz F
bz E
bx D
bx C
b0 B
bx A
bx @
bx ?
x>
x=
bx <
x;
x:
x9
x8
bx 7
bx 6
b0 5
bx 4
bx 3
bx 2
bx 1
bx 0
bx /
x.
x-
bx ,
bx +
z*
z)
1(
bx '
bx &
0%
bx $
bx #
b0 "
x!
$end
#5
1%
#10
1-
0.
0=
09
0>
0:
08
0;
0%
b1111 '
b1111 ,
0(
#15
bx B
b1111 7
bx "
b1111 0
b0xxxxxxxxxxxxxxx 5
1%
#20
0-
b1111 @
bx ?
1.
1=
19
0%
b1110110000010000 '
b1110110000010000 ,
#25
b1111 $
bx 7
b1111 2
0!
bx 0
1%
#30
1-
bx @
0.
0=
09
0%
b1 '
b1 ,
#35
b1 7
b1 0
1%
#40
0-
b1111111111111110 @
1.
1>
1:
0%
b1010101111001101 &
b1010101111001101 +
b1010101111001101 C
b1110001100001000 '
b1110001100001000 ,
#45
b1 $
b1 2
1!
1%
#50
1-
b1001000110100 7
b0 /
b0 <
b0 A
b0 @
0.
19
1;
0:
0%
b1001000110100 &
b1001000110100 +
b1001000110100 C
b101011001111000 '
b101011001111000 ,
#55
b101011001111000 0
1%
#60
b1010101111001101 7
09
0;
0%
b1010101111001101 &
b1010101111001101 +
b1010101111001101 C
b1001000110100 '
b1001000110100 ,
#65
b1001000110100 0
1%
#70
b1001000110100 7
b1010101111001101 @
0>
0%
b1 '
b1 ,
#75
b1 7
b1 0
1%
#80
0%
b1 '
b1 ,
